analytics_api/__init__.py
analytics_api/database.py
analytics_api/git_analyzer.py
analytics_api/mcp_data_service.py
analytics_api/models.py
analytics_api/server.py
analytics_api/simple_database.py
frontend_dev_assistant/__init__.py
frontend_dev_assistant/call_tracker.py
frontend_dev_assistant/component_finder.py
frontend_dev_assistant/prompt_manager.py
frontend_dev_assistant/usage_tracker.py
frontend_dev_assistant/templates/default_templates.json
mseep_frontend_dev_assistant_mcp-0.1.1.dist-info/METADATA
mseep_frontend_dev_assistant_mcp-0.1.1.dist-info/WHEEL
mseep_frontend_dev_assistant_mcp-0.1.1.dist-info/entry_points.txt
mseep_frontend_dev_assistant_mcp-0.1.1.dist-info/top_level.txt
mseep_frontend_dev_assistant_mcp-0.1.1.dist-info/RECORD
